{"paths":{"0":["image_true-#10542",0],"1":["image_true-#10599",0],"2":["image_true-#10519",0],"3":["image_true-#10582",0],"4":["image_true-#10550",0],"5":["gq67_bj",0],"6":["image_true-#10547",0],"7":["image_true-#10590",0],"8":["image_true-#10523",0],"9":["image_true-#10594",0],"10":["image_true-#10563",0],"11":["image_true-#10523",1,1],"12":["image_true-#10563",1,1],"13":["image_true-#10542",1,1],"14":["image_true-#10547",1,1],"15":["image_true-#10550",1,1],"16":["image_true-#10594",1,1],"17":["image_true-#10590",1,1],"18":["gq67_bj",1,1],"19":["image_true-#10599",1,1],"20":["info",2],"21":["image_true-#10519",1,1],"22":["image_true-#10582",1,1]},"types":["cc.Texture2D","cc.SpriteFrame","cc.JsonAsset"],"uuids":["03vkcm3eVDKKEpUzUScOEP","0dPw/43AJN4qop0Joj9NTK","23FnKaqM1GBpbqfDYxhFXi","27KRuK6wFJdL4x6BMsD2rB","4eIcd8ldJMaZHMV+ArVsd7","85PLZKGfREp4klX/4/GqLK","8budw+vB1EUq0D2G9j4Mlx","97tDHBK+tKvLEPKVyZscoZ","a4WgHEIe1Ed4an2mzfCwt1","c7dLQdx4RLkpsBGsDv7Xeg","d0QPQn2NZBoYzpjNzjKAce","0c5WbwSTFOl79xnhAWvrvq","19YzBBiixLC7icSFZ+8+Sm","3eKUA21X1OEIzd/9LaNuvb","3exW8amGNAsZc0g9CIkNIt","5elaFrRwJIdacPx7X7w4pN","68o3tPVdpBPZx3SEKb7158","77KYDQOJtCsL5VC6+m4ndy","aeMqPsYYZLMJRoVzxz6yI9","d5GuEZwu9AkqEiKXV4i3xF","dfmsobENZP0IioajfUzNHn","e3l2igaxlJT6Z9FHhf5VBb","e4C5ge9xZDsaguYfXG/Fu7"],"scenes":{},"redirect":[],"deps":[],"packs":{"0495a27c9":[0,1,2,3,4,5,6,7,8,9,10]},"name":"findFault_stage67","importBase":"import","nativeBase":"native","debug":false,"isZip":false,"encrypted":false,"versions":{"import":["0495a27c9","0f357",11,"c5640",12,"80f34",13,"b701a",14,"51966",15,"f9478",16,"f85dc",17,"de8bc",18,"3fbe6",19,"c03be",20,"d3540",21,"937fb",22,"bf822"],"native":[0,"a2cc1",1,"8a6bb",2,"ed84e",3,"a11b6",4,"64cb3",5,"16ab1",6,"92de8",7,"ef722",8,"341cf",9,"9b193",10,"6645f"]}}