[1,["ecpdLyjvZBwrvm+cedCcQy","a4uIwF23NMJ77Cp29F3QHy","23ZM0WkBRBnKxFfVaLt4rA"],["node","root","obs","endPoint","startPoint","data","_spriteFrame","_textureSetter"],[["cc.Node",["_name","_prefab","_parent","_components","_contentSize","_children","_trs"],2,4,1,9,5,2,7],["cc.PrefabInfo",["fileId","root","asset"],2,1,1],["cc.PhysicsPolygonCollider",["node","points","_offset"],3,1,12,5],"cc.SpriteFrame",["cc.Prefab",["_name"],2],["0eb20kRkqdDFYiydKEEOvgY",["node","startPoint","endPoint","obs"],3,1,1,1,1],["cc.Sprite",["node","_materials","_spriteFrame"],3,1,3,6],["cc.RigidBody",["_type","_allowSleep","node"],1,1]],[[1,0,1,2,2],[0,0,2,1,6,2],[4,0,2],[0,0,5,3,1,4,2],[0,0,2,3,1,4,2],[0,0,2,1,2],[5,0,1,2,3,1],[1,1,2,1],[6,0,1,2,1],[7,0,1,2,3],[2,0,1,1],[2,0,2,1,1]],[[[[2,"Level17"],[3,"Level17",[-6,-7,-8,-9],[[6,-5,-4,-3,-2]],[7,-1,0],[5,750,1334]],[4,"LevelRig",1,[[8,-10,[0],1],[9,0,false,-11],[10,-12,[[[0,-469.8,399.7],[0,-469,377.9],[0,-268,379.2],[0,-268,-398],[0,9,-398],[0,8,-250],[0,-139,-252],[0,-139,-268],[0,-9,-268],[0,-9,-381],[0,-251,-381],[0,-251,-139],[0,-121,-139],[0,-121,-9],[0,139,-8],[0,138,9],[0,-139,9],[0,-138,-121],[0,-251,-121],[0,-251,121],[0,-121,121],[0,-121,138],[0,-251,138],[0,-251,381],[0,-121,381],[0,-121,398]],8,8,8,8,8,8,8,8,8,8,8,8,8,8,8,8,8,8,8,8,8,8,8,8,8,8]],[11,-13,[0,65,0],[[[0,-73.5,398],[0,-73.5,268],[0,-203.5,268],[0,-202.5,251],[0,-73.5,251],[0,-73.5,121],[0,-55.5,121],[0,-55.5,381],[0,186.5,381],[0,186.5,138],[0,74.5,138],[0,74.5,268],[0,56.5,268],[0,56.5,121],[0,186.5,121],[0,186.5,-381],[0,74.5,-381],[0,74.5,-121],[0,-73.5,-121],[0,-73.5,-138],[0,56.5,-139],[0,56.5,-398],[0,203.5,-398],[0,203.5,382.2],[0,419,379.6],[0,418.7,397.3]],8,8,8,8,8,8,8,8,8,8,8,8,8,8,8,8,8,8,8,8,8,8,8,8,8,8]]],[0,"73NwgXCVVHJYfQn8kzgg/z",1,0],[5,536,796]],[1,"StartPoint",1,[0,"1bLl7EZbVFAJxuRWuyiqmG",1,0],[-70.057,271.613,0,0,0,0,1,1,1,1]],[1,"EndPoint",1,[0,"fd5GXz5vpJGYHKo9x/uIl/",1,0],[-68.516,-374.277,0,0,0,0,1,1,1,1]],[5,"obs",1,[0,"6fmLA9gXFHcpGyuYbmaXt9",1,0]]],0,[0,1,1,0,2,5,0,3,4,0,4,3,0,0,1,0,-1,2,0,-2,3,0,-3,4,0,-4,5,0,0,2,0,0,2,0,0,2,0,0,2,0,5,1,13],[0,0],[-1,6],[0,1]],[[{"name":"gq_17","rect":[82,2,536,796],"offset":[0,0],"originalSize":[700,800],"capInsets":[0,0,0,0]}],[3],0,[0],[7],[2]]]]