[1,["ecpdLyjvZBwrvm+cedCcQy","0c1nhTuspMY4LBBrQI7+11","8eTf+MITZK3YSGvMhGU1NJ","ddW+xBdvNDv7eDaPiytXTq","31uzr/SPlLVamPLqXKkVeE","1fjf8l93JCnargANEg4qdY"],["node","_spriteFrame","_N$file","root","skinNode","closeTip","layout","data","prefab","_textureSetter"],[["cc.Node",["_name","_objFlags","_opacity","_prefab","_components","_contentSize","_parent","_children","_trs","_color"],0,4,9,5,1,2,7,5],["cc.PrefabInfo",["fileId","root","asset"],2,1,1],["cc.Sprite",["_sizeMode","_type","_isTrimmedMode","node","_materials","_spriteFrame"],0,1,3,6],"cc.SpriteFrame",["cc.Prefab",["_name"],2],["cc.Node",["_name","_parent","_components","_prefab","_contentSize","_trs"],2,1,2,4,5,7],["cc.Widget",["_alignFlags","_originalWidth","_originalHeight","node"],0,1],["cc.BlockInputEvents",["node"],3,1],["618e4Rz7XdP8IRMsI2OiN6u",["node","layout","closeTip","skinNode","prefab"],3,1,1,1,1,6],["cc.Label",["_string","_fontSize","_lineHeight","_isSystemFontUsed","_N$horizontalAlign","_N$verticalAlign","_N$cacheMode","node","_materials","_N$file"],-4,1,3,6],["cc.LabelOutline",["_width","node","_color"],2,1,5],["ec6c9CRWfRKtbKfEJATpqHM",["_dataID","node"],2,1],["cc.Layout",["_resize","_N$layoutType","_N$spacingX","_N$spacingY","node","_layoutSize"],-1,1,5]],[[1,0,1,2,2],[0,0,6,4,3,5,8,2],[6,0,1,2,3,4],[9,0,1,2,3,4,5,6,7,8,9,8],[10,0,1,2,2],[11,0,1,2],[4,0,2],[0,0,1,7,4,3,5,3],[0,0,6,7,3,2],[0,0,2,6,4,3,9,5,3],[5,0,1,2,3,4,5,2],[7,0,1],[8,0,1,2,3,4,1],[1,1,2,1],[2,1,0,3,4,5,3],[2,0,2,3,4,5,3],[12,0,1,2,3,4,5,5]],[[[[6,"UIAssetReceiveView"],[7,"UIAssetReceiveView",512,[-8,-9],[[2,45,750,1334,-2],[11,-3],[12,-7,-6,-5,-4,8]],[13,-1,0],[5,750,1334]],[8,"base",1,[-10,-11,-12,-13],[0,"c7weUUaM9Ed7DoU7kYvdp5",1,0]],[1,"closeTip",2,[[3,"点击任意位置继续",31,31,false,1,1,1,-14,[6],7],[4,2,-15,[4,4278190080]],[5,"Click the screen to continue",-16]],[0,"69aaTD0+NCQ46bPjzNjGSZ",1,0],[5,252,43.06],[2.3120000000000003,-314.096,0,0,0,0,1,1,1,1]],[1,"title",2,[[3,"获得奖励",49,63,false,1,1,1,-17,[4],5],[4,2,-18,[4,4278190080]],[5,"Receive rewards",-19]],[0,"c0PeRjwPRAUJtSRVAWgzob",1,0],[5,200,83.38],[1,437.414,0,0,0,0,1,1,1,1]],[9,"background",160,1,[[14,1,0,-20,[0],1],[2,45,750,1334,-21]],[0,"7acR1imTdDbbVaeIVRJrmg",1,0],[4,4278190080],[5,750,1334]],[1,"light",2,[[15,2,false,-22,[2],3]],[0,"16j4uNAKtLxZ7UuGynmkRf",1,0],[5,613,613],[0,104,0,0,0,0,1,1,1,1]],[10,"layout",2,[-23],[0,"a1WHDNWWlIEashcmLAZezs",1,0],[5,93,95],[0,101,0,0,0,0,1,1,1,1]],[16,1,1,30,30,7,[5,93,95]]],0,[0,3,1,0,0,1,0,0,1,0,4,6,0,5,3,0,6,8,0,0,1,0,-1,5,0,-2,2,0,-1,6,0,-2,4,0,-3,3,0,-4,7,0,0,3,0,0,3,0,0,3,0,0,4,0,0,4,0,0,4,0,0,5,0,0,5,0,0,6,0,-1,8,0,7,1,23],[0,0,0,0,0,0,0,0,0],[-1,1,-1,1,-1,2,-1,2,8],[0,2,0,3,0,1,0,1,4]],[[{"name":"shop_reward_bglight","rect":[0,0,613,613],"offset":[0,0],"originalSize":[613,613],"capInsets":[0,0,0,0]}],[3],0,[0],[9],[5]]]]