[1,0,0,[["cc.JsonAsset",["_name","json"],1]],[[0,0,1,3]],[[0,"info",{"bgUrl":"gq178_bj","points":[{"url":"gq178_image_1","x":-216.683,"y":137.148,"scaleX":1,"scaleY":1},{"url":"gq178_image_2","x":-21.448,"y":-8.067,"scaleX":1,"scaleY":1},{"url":"gq178_image_3","x":-270.429,"y":-95.416,"scaleX":1,"scaleY":1},{"url":"gq178_image_4","x":-105.782,"y":-110.484,"scaleX":1,"scaleY":1},{"url":"gq178_image_5","x":112.681,"y":-83.046,"scaleX":1,"scaleY":1},{"url":"gq178_image_6","x":93.425,"y":146.938,"scaleX":1,"scaleY":1},{"url":"gq178_image_7","x":254.236,"y":-72.433,"scaleX":1,"scaleY":1},{"url":"gq178_image_8","x":286.819,"y":-183.633,"scaleX":1,"scaleY":1},{"url":"gq178_image_9","x":-33.953,"y":-203.589,"scaleX":1,"scaleY":1},{"url":"gq178_image_10","x":276.369,"y":180.61,"scaleX":1,"scaleY":1}]}]],0,0,[],[],[]]