{"type":"Scene","props":{"width":750,"runtime":"Main/Scenes/Over.ts","height":1334,"autoDestroyAtClosed":false},"compId":2,"child":[{"type":"Panel","props":{"y":0,"x":0,"top":0,"right":0,"left":0,"bottom":0,"bgColor":"#000000","alpha":0.4},"compId":23},{"type":"Button","props":{"var":"btnContinue","stateNum":1,"skin":"ui/game/jsjm_dk_1.png","centerX":0,"bottom":275,"anchorY":0.5,"anchorX":0.5},"compId":8,"child":[{"type":"Image","props":{"y":23,"x":16,"skin":"ui/game/yxjm_zs_1.png","scaleY":1,"scaleX":1},"compId":35},{"type":"FontClip","props":{"y":32,"value":"9999","skin":"ui/game/yxjm_sz_2.png","sheet":"0123456789%*>-./:","scaleY":0.4,"scaleX":0.4,"name":"coinValue","centerX":47},"compId":37}]},{"type":"Image","props":{"x":0,"top":75,"skin":"ui/game/yxjm_wz_1.png","name":"title","centerX":-30},"compId":24,"child":[{"type":"FontClip","props":{"y":-3,"var":"stageValue","value":"99","skin":"ui/game/number.png","sheet":"0123456789%*>-./:","scaleY":0.3,"scaleX":0.3,"centerX":82},"compId":25}]},{"type":"Image","props":{"y":0,"x":0,"width":214,"top":20,"skin":"ui/game/yxjm_gjdk_1.png","name":"coin","left":20,"height":60},"compId":26,"child":[{"type":"Image","props":{"y":7,"x":0,"skin":"ui/game/yxjm_zs_2.png","name":"icon"},"compId":27},{"type":"FontClip","props":{"y":7,"var":"coinValue","value":"9999","skin":"ui/game/number.png","sheet":"0123456789%*>-./:","scaleY":0.3,"scaleX":0.3,"centerX":29},"compId":28}]},{"type":"CheckBox","props":{"var":"videoCheckBox","strokeColors":"#28ff00","stateNum":3,"skin":"ui/game/checkbox.png","labelStrokeColor":"#28ff00","labelSize":35,"labelPadding":"15","labelFont":"Microsoft YaHei","labelColors":"#ffffff","labelBold":true,"label":"看视频领取三倍奖励","centerX":-25,"bottom":450,"anchorY":0,"anchorX":0},"compId":40,"child":[{"type":"Image","props":{"y":10,"x":392,"skin":"ui/game/yxjm_sp_1.png"},"compId":41}]},{"type":"Image","props":{"top":75,"skin":"ui/game/jsjm_tb_1.png","centerX":0},"compId":42,"child":[{"type":"Image","props":{"y":316,"x":227,"skin":"ui/game/jsjm_wz_1.png"},"compId":43}]}],"loadList":["ui/game/jsjm_dk_1.png","ui/game/yxjm_zs_1.png","ui/game/yxjm_sz_2.png","ui/game/yxjm_wz_1.png","ui/game/number.png","ui/game/yxjm_gjdk_1.png","ui/game/yxjm_zs_2.png","ui/game/checkbox.png","ui/game/yxjm_sp_1.png","ui/game/jsjm_tb_1.png","ui/game/jsjm_wz_1.png"],"loadList3D":[]}