{"paths":{"0":["gq35_bj",0],"1":["image_true-#4133",0],"2":["gq35_image_5",0],"3":["image_true-#4118",0],"4":["image_true-#4157",0],"5":["image_true-#4156",0],"6":["image_true-#4073",0],"7":["image_true-#4107",0],"8":["image_true-#4128",0],"9":["image_true-#4168",0],"10":["image_true-#4136",0],"11":["image_true-#4164",0],"12":["image_true-#4157",1,1],"13":["image_true-#4073",1,1],"14":["image_true-#4107",1,1],"15":["gq35_image_5",1,1],"16":["image_true-#4168",1,1],"17":["image_true-#4118",1,1],"18":["info",2],"19":["image_true-#4164",1,1],"20":["image_true-#4136",1,1],"21":["image_true-#4156",1,1],"22":["gq35_bj",1,1],"23":["image_true-#4128",1,1],"24":["image_true-#4133",1,1]},"types":["cc.Texture2D","cc.SpriteFrame","cc.JsonAsset"],"uuids":["07lRO8PuxJH63yCmqpSZKS","52d07BlepDT77J3xLpJ/YK","5f06vzYG9PEZffQ7dvv/8i","6fvPrG4ydLLbCgh8Dx4jkW","76ExNmf9NCQoTt24geF0rj","78mxIjLO5GP7TOoMnEqYY6","7e6MV1sUZL9pXq+Q5k5mf8","a85BZu5Z9EmIbYG93nl4wL","b94lBxnHNPPbLXXdiP/d00","d5Z38BH/pLqaSEBKolK8em","e4zkL+n+lJ7Ky6rdHg5rdU","e6Pt9KBpZEUpEnb4f+Ay+i","05qcXuTFNLT6yaoSk+8Ftv","0ffU4vzjxMTquiFYt+T7Wh","15g4ZjaVJD6J4e44MJ5JTy","1c10dM79NMXJaeEzPYzAFb","23anqtW71MHIW1nOsdRJ0R","44qxbbAAJKypxid5ra5gnP","629o8uMpJITKABKvf7cgIS","98RCvNhwVL3axzylF0Wug3","b06bi2nTNEhLJ3XzTY/R0h","b6G7eJ2jZOb5STG5dxc1UW","bfB9H/sV1Ahajxel25KuHE","ceamwrXslLo7fwZ/N74Sh/","d3V5E3WxVC96I5fozyhrWe"],"scenes":{},"redirect":[],"deps":[],"packs":{"07a4c5fb1":[0,1,2,3,4,5,6,7,8,9,10,11]},"name":"findFault_stage35","importBase":"import","nativeBase":"native","debug":false,"isZip":false,"encrypted":false,"versions":{"import":[12,"b544b","07a4c5fb1","7f7ca",13,"2f220",14,"a85b1",15,"995f8",16,"28358",17,"d768d",18,"05fff",19,"1f58f",20,"5313a",21,"49afd",22,"59e3d",23,"3e976",24,"7e2d6"],"native":[0,"1b0f1",1,"eb388",2,"dbda4",3,"63013",4,"50e60",5,"ed522",6,"ec579",7,"14fc7",8,"727c7",9,"faa28",10,"7e454",11,"ff377"]}}