[1,0,0,[["cc.JsonAsset",["_name","json"],1]],[[0,0,1,3]],[[0,"info",{"bgUrl":"gq168_bj","points":[{"url":"gq168_image_1","x":-231.22,"y":169.157,"scaleX":1,"scaleY":1},{"url":"gq168_image_2","x":-329.912,"y":59.151,"scaleX":1,"scaleY":1},{"url":"gq168_image_3","x":-121.032,"y":-102.3,"scaleX":1,"scaleY":1},{"url":"gq168_image_4","x":-29.299,"y":46.63,"scaleX":1,"scaleY":1},{"url":"gq168_image_5","x":3.807,"y":-49.984,"scaleX":1,"scaleY":1},{"url":"gq168_image_6","x":71.456,"y":-165.626,"scaleX":1,"scaleY":1},{"url":"gq168_image_7","x":144.932,"y":-72.639,"scaleX":1,"scaleY":1},{"url":"gq168_image_8","x":230.256,"y":-14.207,"scaleX":1,"scaleY":1},{"url":"gq168_image_9","x":258.392,"y":-176.416,"scaleX":1,"scaleY":1},{"url":"gq168_image_10","x":-220.751,"y":-13.679,"scaleX":1,"scaleY":1}]}]],0,0,[],[],[]]